[{
    "name": "Machu Picchu",
    "slug": "machu_picchu",
    "country": "Peru",
    "location": {
        "lat": -13.1631371,
        "lng": -72.5470923
    }
}, {
    "name": "Whitsunday Islands",
    "slug": "whitsunday_islands",
    "country": "Australien",
    "location": {
        "lat": -20.1858647,
        "lng": 148.5867708
    }
}, {
    "name": "Nordkap, Norwegen",
    "slug": "nordkap_norwegen",
    "country": "Norwegen",
    "location": {
        "lat": 71.170955,
        "lng": 25.7814712
    }
}]